Metadata-Version: 2.1
Name: modelChooserTransfer
Version: 0.0.1
Summary: ferramenta para adaptacao de dominio com transfer learning
Author: Pedro Henrique Conrado Ferreira de Oliveira
Author-email: pedrohenriqueconrado@usp.br
License: MIT License
Keywords: transfer domain adaptation keras
License-File: LICENSE
